{
  "extra_params": {
    "n": 10,
    "m": 0,
    "shape": "square",
    "integer_size": true,
    "size_min": 2,
    "size_max": 8,
    "overlap_fraction": 0.0,
    "overlap_degree": 0.0,
    "grid_size": 50,
    "seed": 1010,
    "workers": 4,
    "threads": 16,
    "time_limit": 1800,
    "mip_focus": 3,
    "time_heuristic_s": 0.2805,
    "time_gurobi_s": 1806.6974
  },
  "graph": {
    "grid_size": 50,
    "neighborhoods": [
      {
        "type": "square",
        "cx": 42,
        "cy": 19,
        "side": 7
      },
      {
        "type": "square",
        "cx": 9,
        "cy": 30,
        "side": 6
      },
      {
        "type": "square",
        "cx": 29,
        "cy": 13,
        "side": 5
      },
      {
        "type": "square",
        "cx": 29,
        "cy": 48,
        "side": 3
      },
      {
        "type": "square",
        "cx": 8,
        "cy": 48,
        "side": 3
      },
      {
        "type": "square",
        "cx": 45,
        "cy": 36,
        "side": 6
      },
      {
        "type": "square",
        "cx": 20,
        "cy": 39,
        "side": 4
      },
      {
        "type": "square",
        "cx": 41,
        "cy": 26,
        "side": 5
      },
      {
        "type": "square",
        "cx": 8,
        "cy": 4,
        "side": 6
      },
      {
        "type": "square",
        "cx": 37,
        "cy": 39,
        "side": 6
      }
    ],
    "edges": [
      [
        0,
        1
      ],
      [
        0,
        2
      ],
      [
        0,
        3
      ],
      [
        0,
        4
      ],
      [
        0,
        5
      ],
      [
        0,
        6
      ],
      [
        0,
        7
      ],
      [
        0,
        8
      ],
      [
        0,
        9
      ],
      [
        1,
        2
      ],
      [
        1,
        3
      ],
      [
        1,
        4
      ],
      [
        1,
        5
      ],
      [
        1,
        6
      ],
      [
        1,
        7
      ],
      [
        1,
        8
      ],
      [
        1,
        9
      ],
      [
        2,
        3
      ],
      [
        2,
        4
      ],
      [
        2,
        5
      ],
      [
        2,
        6
      ],
      [
        2,
        7
      ],
      [
        2,
        8
      ],
      [
        2,
        9
      ],
      [
        3,
        4
      ],
      [
        3,
        5
      ],
      [
        3,
        6
      ],
      [
        3,
        7
      ],
      [
        3,
        8
      ],
      [
        3,
        9
      ],
      [
        4,
        5
      ],
      [
        4,
        6
      ],
      [
        4,
        7
      ],
      [
        4,
        8
      ],
      [
        4,
        9
      ],
      [
        5,
        6
      ],
      [
        5,
        7
      ],
      [
        5,
        8
      ],
      [
        5,
        9
      ],
      [
        6,
        7
      ],
      [
        6,
        8
      ],
      [
        6,
        9
      ],
      [
        7,
        8
      ],
      [
        7,
        9
      ],
      [
        8,
        9
      ]
    ]
  },
  "heuristic": {
    "positions": [
      [
        38.5,
        20.16353461189624
      ],
      [
        12.0,
        33.0
      ],
      [
        26.5,
        13.57701307015256
      ],
      [
        27.5,
        46.5
      ],
      [
        9.5,
        46.5
      ],
      [
        42.0,
        33.330201278553204
      ],
      [
        18.0,
        41.0
      ],
      [
        40.25,
        26.73735947755561
      ],
      [
        11.0,
        7.0
      ],
      [
        34.75,
        39.910346407403054
      ]
    ],
    "mst": [
      [
        0,
        7,
        6.802769536325735
      ],
      [
        5,
        7,
        6.821148218077451
      ],
      [
        5,
        9,
        9.790853380412068
      ],
      [
        3,
        9,
        9.797246269765083
      ],
      [
        1,
        6,
        10.0
      ],
      [
        4,
        6,
        10.124228365658293
      ],
      [
        3,
        6,
        10.977249200050075
      ],
      [
        0,
        2,
        13.68876422544612
      ],
      [
        2,
        8,
        16.83766910605377
      ]
    ],
    "cost": 94.83992830178859,
    "original_cost": 117.53272859602214,
    "k": 32
  },
  "gurobi": {
    "positions": [
      [
        38.5,
        22.5
      ],
      [
        12.0,
        33.0
      ],
      [
        26.50000059309605,
        15.499999687103545
      ],
      [
        27.5,
        46.5
      ],
      [
        9.5,
        46.5
      ],
      [
        42.0,
        33.0
      ],
      [
        18.0,
        41.0
      ],
      [
        39.867363955483285,
        26.602091810521248
      ],
      [
        11.0,
        7.0
      ],
      [
        35.95032725239698,
        38.63245402004489
      ]
    ],
    "mst": [
      [
        0,
        2,
        13.89244363480542
      ],
      [
        0,
        7,
        4.323984436685727
      ],
      [
        1,
        6,
        10.0
      ],
      [
        2,
        8,
        17.677669899246855
      ],
      [
        3,
        6,
        10.977249200050075
      ],
      [
        3,
        9,
        11.545835197997194
      ],
      [
        4,
        6,
        10.124228365658293
      ],
      [
        5,
        7,
        6.7439873739036
      ],
      [
        5,
        9,
        8.265777558161753
      ]
    ],
    "cost": 93.55117566650894,
    "stats": {
      "status": 9,
      "obj_val": 93.55116881816399,
      "obj_bound": 93.41705691704787,
      "mip_gap": 0.0014335673494019964,
      "runtime_s": 1800.0821118354797,
      "node_count": 5025580,
      "sol_count": 8,
      "n": 10
    },
    "log": "\nGurobi 11.0.3 (linux64) logging started Sun Mar  8 23:28:03 2026\n\n"
  }
}